LICENSE
README.md
setup.py
tuf_manifest/__init__.py
tuf_manifest/tuf_manifest_client.py
tuf_manifest/tuf_manifest_repo.py
tuf_manifest.egg-info/PKG-INFO
tuf_manifest.egg-info/SOURCES.txt
tuf_manifest.egg-info/dependency_links.txt
tuf_manifest.egg-info/top_level.txt
tuf_manifest/scripts/tufm-client
tuf_manifest/scripts/tufm-repo