Metadata-Version: 2.1
Name: tuf-manifest
Version: 0.0.3
Summary: A layer on top of tuf to provide file delivery with manifests
Home-page: https://github.com/MontaVista-OpenSourceTechnology/tuf_manifest
Author: Corey Minyard
Author-email: cminyard@mvista.com
License: UNKNOWN
Platform: UNKNOWN
Classifier: License :: OSI Approved :: MIT License
Classifier: Operating System :: OS Independent
